graphpatch/__init__.py
graphpatch/exceptions.py
graphpatch/extraction/__init__.py
graphpatch/extraction/compiled_graph_module.py
graphpatch/extraction/extraction_context.py
graphpatch/extraction/extraction_options.py
graphpatch/extraction/graph_extraction.py
graphpatch/extraction/graphpatch_module.py
graphpatch/extraction/multiply_invoked_module.py
graphpatch/extraction/opaque_graph_module.py
graphpatch/extraction/wrapped_8_bit_linear.py
graphpatch/extraction/wrapped_layer_norm.py
graphpatch/hacks.py
graphpatch/meta/__init__.py
graphpatch/meta/graph_meta.py
graphpatch/meta/node_data.py
graphpatch/meta/node_path.py
graphpatch/optional/__init__.py
graphpatch/optional/accelerate.py
graphpatch/optional/bitsandbytes.py
graphpatch/optional/dataclasses.py
graphpatch/optional/transformer_lens.py
graphpatch/optional/transformers.py
graphpatch/optional/typing_extensions.py
graphpatch/patch.py
graphpatch/patchable_graph.py
graphpatch-0.2.3.dist-info/LICENSE
graphpatch-0.2.3.dist-info/METADATA
graphpatch-0.2.3.dist-info/WHEEL
graphpatch-0.2.3.dist-info/RECORD
