Metadata-Version: 2.1
Name: graphpatch
Version: 0.2.3
Summary: graphpatch is a library for activation patching on PyTorch neural network models.
Home-page: https://www.graphpatch.dev
License: MIT
Keywords: mechanistic interpretability,interpretability,pytorch,torch,activation patch,ablation,transformer,large language model,llm
Author: Evan Lloyd
Author-email: evan.t.lloyd@gmail.com
Requires-Python: >=3.8.1,<3.13
Classifier: Development Status :: 4 - Beta
Classifier: License :: OSI Approved :: MIT License
Classifier: Programming Language :: Python :: 3
Classifier: Programming Language :: Python :: 3.9
Classifier: Programming Language :: Python :: 3.10
Classifier: Programming Language :: Python :: 3.11
Classifier: Programming Language :: Python :: 3.12
Provides-Extra: transformer-lens
Provides-Extra: transformers
Requires-Dist: accelerate (>=0.15.0) ; extra == "transformers"
Requires-Dist: bitsandbytes (>=0.35.4) ; (sys_platform != "darwin") and (extra == "transformers")
Requires-Dist: numpy (>=1.17) ; python_version >= "3.10"
Requires-Dist: numpy (>=1.17,<1.25) ; python_version < "3.9"
Requires-Dist: numpy (>=1.17,<2.1) ; python_version >= "3.9" and python_version < "3.10"
Requires-Dist: sentencepiece (>=0.1.94) ; extra == "transformers"
Requires-Dist: torch (>=2.0,<2.5) ; python_version >= "3.8" and python_version < "3.9"
Requires-Dist: torch (>=2.0,<2.6) ; python_version >= "3.9" and python_version < "3.11"
Requires-Dist: torch (>=2.1,<2.6) ; python_version >= "3.11" and python_version < "3.12"
Requires-Dist: torch (>=2.4,<2.6) ; python_version >= "3.12"
Requires-Dist: transformer-lens (>=1.16.0) ; extra == "transformer-lens"
Requires-Dist: transformers (>=4.28.0) ; extra == "transformers"
Project-URL: Documentation, https://graphpatch.readthedocs.io/en/latest/index.html
Project-URL: Repository, https://github.com/evan-lloyd/graphpatch
